speechloop/__init__.py
speechloop/core.py
speechloop/file_utils.py
speechloop/hash_utils.py
speechloop/live.py
speechloop/main.py
speechloop/model_runner.py
speechloop/run_arguments.py
speechloop/shared_args.py
speechloop/summary.py
speechloop/text.py
speechloop/validate.py
speechloop/wizard.py
speechloop/asr/__init__.py
speechloop/asr/aws.py
speechloop/asr/azure.py
speechloop/asr/base_asr.py
speechloop/asr/container_utils.py
speechloop/asr/coqui.py
speechloop/asr/errors.py
speechloop/asr/google.py
speechloop/asr/registry.py
speechloop/asr/sphinx.py
speechloop/asr/vosk.py
speechloop/data/simple_test/README.md
speechloop/data/simple_test/simple_test.csv
speechloop/data/simple_test/simple_test2.csv
speechloop/data/simple_test/wavs/109862_airplane_ch0_16k.wav
speechloop/data/simple_test/wavs/109863_ant_ch0_16k.wav
speechloop/data/simple_test/wavs/109864_apple_ch0_16k.wav
speechloop/data/simple_test/wavs/109865_bear_ch0_16k.wav
speechloop/data/simple_test/wavs/109866_boat_ch0_16k.wav
speechloop/data/simple_test/wavs/109867_butterfly_ch0_16k.wav
speechloop/data/simple_test/wavs/109868_camera_ch0_16k.wav
speechloop/data/simple_test/wavs/109869_car_ch0_16k.wav
speechloop/data/simple_test/wavs/109870_cow_ch0_16k.wav
speechloop/data/simple_test/wavs/109871_daisy_ch0_16k.wav
speechloop/data/simple_test/wavs/109872_dog_ch0_16k.wav
speechloop/data/simple_test/wavs/109873_duck_ch0_16k.wav
speechloop/data/simple_test/wavs/109874_earth_ch0_16k.wav
speechloop/data/simple_test/wavs/109875_egg_ch0_16k.wav
speechloop/data/simple_test/wavs/109876_elephant_ch0_16k.wav
speechloop/data/simple_test/wavs/109877_fire_ch0_16k.wav
speechloop/data/simple_test/wavs/109878_fork_ch0_16k.wav
speechloop/data/simple_test/wavs/109879_frog_ch0_16k.wav
speechloop/data/simple_test/wavs/109880_galaxy_ch0_16k.wav
speechloop/data/simple_test/wavs/109881_glass_ch0_16k.wav
speechloop/data/simple_test/wavs/109882_glove_ch0_16k.wav
speechloop/data/simple_test/wavs/109883_hammer_ch0_16k.wav
speechloop-0.0.3.dist-info/AUTHORS.rst
speechloop-0.0.3.dist-info/LICENSE
speechloop-0.0.3.dist-info/METADATA
speechloop-0.0.3.dist-info/WHEEL
speechloop-0.0.3.dist-info/entry_points.txt
speechloop-0.0.3.dist-info/top_level.txt
speechloop-0.0.3.dist-info/RECORD
