Metadata-Version: 2.1
Name: speechloop
Version: 0.0.3
Summary: A "keep it simple" collection of many speech recognition engines... Designed to help answer - what is the best ASR?
Home-page: https://github.com/robmsmt/SpeechLoop
Author: robmsmt
Author-email: robmsmt@gmail.com
Keywords: speech,testing,asr
Classifier: Programming Language :: Python :: 3
Classifier: Programming Language :: Python :: 3 :: Only
Classifier: Programming Language :: Python :: 3.6
Classifier: Programming Language :: Python :: 3.7
Classifier: Programming Language :: Python :: 3.8
Classifier: Programming Language :: Python :: 3.9
Classifier: License :: OSI Approved :: Apache Software License
Classifier: Operating System :: OS Independent
Classifier: Development Status :: 3 - Alpha
Requires-Python: >=3.6
License-File: LICENSE
License-File: AUTHORS.rst
Requires-Dist: amazon-transcribe (==0.6.0)
Requires-Dist: commoncorrections (==1.0.12)
Requires-Dist: docker (==5.0.3)
Requires-Dist: google-cloud-speech (==2.14.1)
Requires-Dist: pandas (==1.4.3)
Requires-Dist: questionary (==1.10.0)
Requires-Dist: simplepythonwer (==1.0.3)
Requires-Dist: sounddevice (==0.4.4)
Requires-Dist: soundfile (==0.10.3.post1)
Requires-Dist: tqdm (==4.64.0)
Requires-Dist: websockets (==10.3)
